{
  "cluster_id": "ngc_6531",
  "cg_name": "NGC_6531",
  "n_rows": 158,
  "n_cg_member": 158,
  "n_with_gaia": 158,
  "n_with_w2": 25,
  "n_with_ruwe": 129,
  "gaia_frac": 1.0,
  "w2_frac": 0.1582,
  "parquet_path": "/app/research/data/processed/t1/members/ngc_6531.parquet",
  "parquet_bytes": 17526,
  "fetched": true,
  "fetch_counts": {
    "cg": 160,
    "gaia": 56033,
    "wise": 6809
  },
  "task": "ingest_cluster",
  "blob_parquet": "processed/t1/members/midas-t1-1781364581/ngc_6531.parquet"
}