{
  "cluster_id": "ngc_2455",
  "cg_name": "NGC_2455",
  "n_rows": 106,
  "n_cg_member": 106,
  "n_with_gaia": 106,
  "n_with_w2": 94,
  "n_with_ruwe": 106,
  "gaia_frac": 1.0,
  "w2_frac": 0.8868,
  "parquet_path": "/app/research/data/processed/t1/members/ngc_2455.parquet",
  "parquet_bytes": 15908,
  "fetched": true,
  "fetch_counts": {
    "cg": 108,
    "gaia": 16183,
    "wise": 4748
  },
  "task": "ingest_cluster",
  "blob_parquet": "processed/t1/members/midas-t1-1781364581/ngc_2455.parquet"
}